dwh_oppfolging/README.md
dwh_oppfolging/__init__.py
dwh_oppfolging/apis/__init__.py
dwh_oppfolging/apis/airflow_api_v1.py
dwh_oppfolging/apis/bigquery_api_v1.py
dwh_oppfolging/apis/brreg_api_v2.py
dwh_oppfolging/apis/dbt_oracle_api_v1.py
dwh_oppfolging/apis/generic_api_v1.py
dwh_oppfolging/apis/kafka_api_v1.py
dwh_oppfolging/apis/kafka_api_v1_types.py
dwh_oppfolging/apis/oracle_api_v1.py
dwh_oppfolging/apis/oracle_api_v1_types.py
dwh_oppfolging/apis/secrets_api_v1.py
dwh_oppfolging/apis/ssb_api_v1.py
dwh_oppfolging/apis/ssb_api_v1_types.py
dwh_oppfolging/transforms/__init__.py
dwh_oppfolging/transforms/datatypes.py
dwh_oppfolging/transforms/functions.py
dwh_oppfolging-0.1.95.dist-info/LICENSE
dwh_oppfolging-0.1.95.dist-info/METADATA
dwh_oppfolging-0.1.95.dist-info/WHEEL
dwh_oppfolging-0.1.95.dist-info/RECORD
