Metadata-Version: 2.3
Name: dwh-oppfolging
Version: 0.1.95
Summary: Oppfolging python package for DWH ETL
Author: Team Oppfølging
Requires-Python: ==3.12.*
Classifier: Programming Language :: Python :: 3
Classifier: Programming Language :: Python :: 3.12
Requires-Dist: confluent-kafka[avro,json,schemaregistry] (==2.11.0)
Requires-Dist: dbt-oracle (==1.9.3)
Requires-Dist: fastavro (==1.12.0)
Requires-Dist: google-cloud-bigquery (==3.35.1)
Requires-Dist: google-cloud-secret-manager (==2.24.0)
Requires-Dist: ijson (==3.4.0)
Requires-Dist: numpy (==2.3.2)
Requires-Dist: oracledb (==3.2.0)
Requires-Dist: pendulum (==3.1.0)
Requires-Dist: plotly (==6.3.0)
Requires-Dist: pydantic (==2.11.7)
Requires-Dist: requests (==2.32.4)
